{
  "_meta": {
    "version": "2.5.6",
    "generated": "2026-02-03T23:15:41.912Z",
    "url": "https://raw.githubusercontent.com/facebook/rapid/main/dist/data/shortcuts.json",
    "hash": "d70ade4ea30c26fb1d8ef00b06924a0d"
  },
  "shortcuts": [
    {
      "tab": "browsing",
      "text": "shortcuts.browsing",
      "columns": [
        {
          "rows": [
            {
              "section": "navigation",
              "text": "shortcuts.navigation"
            },
            {
              "shortcuts": ["{interaction-twofinger-tap-and-drag}", "{interaction-keyboard-arrows-all}"],
              "text": "shortcuts.command.pan.label"
            },
            {
              "modifiers": ["⌘"],
              "shortcuts": ["{interaction-keyboard-arrows-all}"],
              "text": "shortcuts.command.pan_more.label"
            },
            {
              "shortcuts": ["{interaction-mouse-wheel}", "{interaction-twofinger-zoom}", ["+", "-"]],
              "text": "shortcuts.command.zoom.label"
            },
            {
              "modifiers": ["⌘"],
              "shortcuts": [["+", "-"]],
              "text": "shortcuts.command.zoom_more.label"
            },
            {
              "modifiers": ["⌥"],
              "shortcuts": ["{interaction-mouse-left}", "{interaction-onefinger-tap}"],
              "text": "shortcuts.command.rotate_map.label"
            },
            {
              "modifiers": ["⇧"],
              "shortcuts": ["{interaction-keyboard-arrows-left-right}"],
              "text": "shortcuts.command.rotate_incremental.label"
            },
            {
              "section": "selecting",
              "text": "shortcuts.selecting_features"
            },
            {
              "shortcuts": ["{interaction-mouse-left}", "{interaction-onefinger-tap}", "shortcuts.key.space"],
              "text": "shortcuts.command.select_one.label"
            },
            {
              "modifiers": ["⇧"],
              "shortcuts": ["{interaction-mouse-left}", "{interaction-onefinger-tap}", "shortcuts.key.space"],
              "text": "shortcuts.command.select_multi.label"
            },
            {
              "modifiers": ["⇧"],
              "shortcuts": ["{interaction-mouse-left}", "{interaction-onefinger-tap-and-drag}"],
              "gesture": "shortcuts.gesture.drag",
              "text": "shortcuts.command.lasso.label"
            },
            {
              "section": "with_selected",
              "text": "shortcuts.with_features_selected"
            },
            {
              "shortcuts": ["{interaction-mouse-right}", "{interaction-onefinger-tap-and-hold}", "☰"],
              "text": "shortcuts.command.edit_menu.label"
            },
            {
              "shortcuts": ["shortcuts.command.zoom_to.key"],
              "text": "shortcuts.command.zoom_to.label"
            }
          ]
        },
        {
          "rows": [
            {
              "section": "node_selected",
              "text": "shortcuts.with_node_selected"
            },
            {
              "shortcuts": ["[", "↖"],
              "text": "shortcuts.command.previous_node.label"
            },
            {
              "shortcuts": ["]", "↘"],
              "text": "shortcuts.command.next_node.label"
            },
            {
              "shortcuts": ["{", "⇞"],
              "text": "shortcuts.command.first_node.label"
            },
            {
              "shortcuts": ["}", "⇟"],
              "text": "shortcuts.command.last_node.label"
            },
            {
              "shortcuts": ["\\", "shortcuts.key.pause"],
              "text": "shortcuts.command.change_parent.label"
            },
            {
              "modifiers": ["⌘"],
              "shortcuts": ["{interaction-keyboard-arrows-up}"],
              "text": "shortcuts.command.select_parent.label"
            },
            {
              "section": "way_selected",
              "text": "shortcuts.with_way_selected"
            },
            {
              "modifiers": ["⌘"],
              "shortcuts": ["{interaction-keyboard-arrows-down}"],
              "text": "shortcuts.command.select_children.label"
            },
            {
              "section": "rapid",
              "text": "shortcuts.with_rapid_selected"
            },
            {
              "shortcuts": ["shortcuts.command.accept_feature.key"],
              "text": "shortcuts.command.accept_feature.label"
            },
            {
              "shortcuts": ["shortcuts.command.ignore_feature.key"],
              "text": "shortcuts.command.ignore_feature.label"
            },
            {
              "section": "photo_selected",
              "text": "shortcuts.with_photo_selected"
            },
            {
              "shortcuts": ["{interaction-keyboard-arrows-up-down}"],
              "text": "shortcuts.command.follow_sequence.label"
            }
          ]
        }
      ]
    },
    {
      "tab": "editing",
      "text": "shortcuts.editing",
      "columns": [
        {
          "rows": [
            {
              "section": "drawing",
              "text": "shortcuts.drawing"
            },
            {
              "shortcuts": ["shortcuts.command.add_point.key"],
              "text": "shortcuts.command.add_point.label"
            },
            {
              "shortcuts": ["shortcuts.command.add_line.key"],
              "text": "shortcuts.command.add_line.label"
            },
            {
              "shortcuts": ["shortcuts.command.add_area.key"],
              "text": "shortcuts.command.add_area.label"
            },
            {
              "shortcuts": ["shortcuts.command.add_note.key"],
              "text": "shortcuts.command.add_note.label"
            },
            {
              "shortcuts": ["{interaction-mouse-left}", "{interaction-onefinger-tap}", "shortcuts.key.space"],
              "text": "shortcuts.command.place_point.label"
            },
            {
              "shortcuts": ["⌥"],
              "text": "shortcuts.command.disable_snap.label"
            },
            {
              "shortcuts": ["↵", "⎋"],
              "text": "shortcuts.command.stop_line.label"
            },
            {
              "section": "commands",
              "text": "shortcuts.commands"
            },
            {
              "modifiers": ["⌘"],
              "shortcuts": ["C"],
              "text": "shortcuts.command.copy.label"
            },
            {
              "modifiers": ["⌘"],
              "shortcuts": ["V"],
              "text": "shortcuts.command.paste.label"
            },
            {
              "modifiers": ["⌘"],
              "shortcuts": ["Z"],
              "text": "shortcuts.command.undo.label"
            },
            {
              "modifiers": ["⌘", "⇧"],
              "shortcuts": ["Z"],
              "text": "shortcuts.command.redo.label"
            },
            {
              "modifiers": ["⌘"],
              "shortcuts": ["S"],
              "text": "shortcuts.command.save.label"
            },
            {
              "modifiers": ["⌘"],
              "shortcuts": ["F"],
              "text": "shortcuts.command.find.label"
            }
          ]
        },
        {
          "rows": [
            {
              "section": "operations",
              "text": "shortcuts.operations"
            },
            {
              "shortcuts": ["{interaction-keyboard-arrows-all}", "shortcuts.command.move.key"],
              "text": "shortcuts.command.move.label"
            },
            {
              "modifiers": ["⇧"],
              "shortcuts": ["{interaction-keyboard-arrows-left-right}", "shortcuts.command.rotate.key"],
              "text": "shortcuts.command.rotate.label"
            },
            {
              "shortcuts": ["shortcuts.command.orthogonalize.key"],
              "text": "shortcuts.command.orthogonalize.label"
            },
            {
              "shortcuts": ["shortcuts.command.straighten.key"],
              "text": "shortcuts.command.straighten.label"
            },
            {
              "shortcuts": ["shortcuts.command.circularize.key"],
              "text": "shortcuts.command.circularize.label"
            },
            {
              "shortcuts": ["shortcuts.command.continue_line.key"],
              "text": "shortcuts.command.continue_line.label"
            },
            {
              "shortcuts": ["shortcuts.command.merge.key"],
              "text": "shortcuts.command.merge.label"
            },
            {
              "shortcuts": ["shortcuts.command.disconnect.key"],
              "text": "shortcuts.command.disconnect.label"
            },
            {
              "shortcuts": ["shortcuts.command.extract.key"],
              "text": "shortcuts.command.extract.label"
            },
            {
              "shortcuts": ["shortcuts.command.split.key"],
              "text": "shortcuts.command.split.label"
            },
            {
              "shortcuts": ["shortcuts.command.reverse.key"],
              "text": "shortcuts.command.reverse.label"
            },
            {
              "shortcuts": ["shortcuts.command.reflect_long.key"],
              "text": "shortcuts.command.reflect_long.label"
            },
            {
              "shortcuts": ["shortcuts.command.reflect_short.key"],
              "text": "shortcuts.command.reflect_short.label"
            },
            {
              "modifiers": ["⌘"],
              "shortcuts": ["⌫"],
              "text": "shortcuts.command.delete.label"
            },
            {
              "modifiers": ["⇧"],
              "shortcuts": ["shortcuts.command.cycle_highway_tag.key"],
              "text": "shortcuts.command.cycle_highway_tag.label"
            }
          ]
        }
      ]
    },
    {
      "tab": "tools",
      "text": "shortcuts.tools",
      "columns": [
        {
          "rows": [
            {
              "section": "help",
              "text": "shortcuts.help"
            },
            {
              "shortcuts": ["shortcuts.command.toggle_help.key"],
              "text": "shortcuts.command.toggle_help.label"
            },
            {
              "shortcuts": ["shortcuts.command.keyboard_shortcuts.key", "?"],
              "text": "shortcuts.command.keyboard_shortcuts.label"
            },
            {
              "section": "display_options",
              "text": "shortcuts.display_options"
            },
            {
              "shortcuts": ["shortcuts.command.toggle_background.key"],
              "text": "shortcuts.command.toggle_background.label"
            },
            {
              "modifiers": ["⌘"],
              "shortcuts": ["shortcuts.command.background_switch.key"],
              "text": "shortcuts.command.background_switch.label"
            },
            {
              "shortcuts": ["shortcuts.command.background_previous.key"],
              "text": "shortcuts.command.background_previous.label"
            },
            {
              "shortcuts": ["shortcuts.command.background_next.key"],
              "text": "shortcuts.command.background_next.label"
            },
            {
              "shortcuts": ["shortcuts.command.toggle_map_data.key"],
              "text": "shortcuts.command.toggle_map_data.label"
            },
            {
              "shortcuts": ["shortcuts.command.toggle_issues.key"],
              "text": "shortcuts.command.toggle_issues.label"
            },
            {
              "shortcuts": ["shortcuts.command.toggle_preferences.key"],
              "text": "shortcuts.command.toggle_preferences.label"
            },
            {
              "modifiers": ["⌃", "⌘"],
              "shortcuts": ["F"],
              "text": "shortcuts.command.toggle_fullscreen.label"
            },
            {
              "shortcuts": ["shortcuts.command.toggle_inspector.key", "`", "²"],
              "text": "shortcuts.command.toggle_inspector.label"
            },
            {
              "shortcuts": ["shortcuts.command.wireframe.key"],
              "text": "shortcuts.command.wireframe.label"
            },
            {
              "shortcuts": ["shortcuts.command.highlight_edits.key"],
              "text": "shortcuts.command.highlight_edits.label"
            }
          ]
        },
        {
          "rows": [
            {
              "section": "viewers",
              "text": "shortcuts.viewers"
            },
            {
              "shortcuts": ["shortcuts.command.toggle_minimap.key"],
              "text": "shortcuts.command.toggle_minimap.label"
            },
            {
              "modifiers": ["⌘"],
              "shortcuts": ["shortcuts.command.toggle_3dmap.key"],
              "text": "shortcuts.command.toggle_3dmap.label"
            },
            {
              "section": "layers",
              "text": "shortcuts.layers"
            },
            {
              "modifiers": ["⇧"],
              "shortcuts": ["shortcuts.command.toggle_all_layers.key"],
              "text": "shortcuts.command.toggle_all_layers.label"
            },
            {
              "modifiers": ["⇧"],
              "shortcuts": ["shortcuts.command.toggle_osm_data.key"],
              "text": "shortcuts.command.toggle_osm_data.label"
            },
            {
              "modifiers": ["⇧"],
              "shortcuts": ["shortcuts.command.toggle_osm_notes.key"],
              "text": "shortcuts.command.toggle_osm_notes.label"
            },
            {
              "modifiers": ["⇧"],
              "shortcuts": ["shortcuts.command.toggle_rapid_data.key"],
              "text": "shortcuts.command.toggle_rapid_data.label"
            },
            {
              "modifiers": ["⇧"],
              "shortcuts": ["shortcuts.command.toggle_mapillary.key"],
              "text": "shortcuts.command.toggle_mapillary.label"
            },
            {
              "modifiers": ["⇧"],
              "shortcuts": ["shortcuts.command.toggle_streetside.key"],
              "text": "shortcuts.command.toggle_streetside.label"
            },
            {
              "modifiers": ["⇧"],
              "shortcuts": ["shortcuts.command.toggle_kartaview.key"],
              "text": "shortcuts.command.toggle_kartaview.label"
            },
            {
              "section": "info",
              "text": "shortcuts.info"
            },
            {
              "modifiers": ["⌘"],
              "shortcuts": ["shortcuts.command.toggle_all_cards.key"],
              "text": "shortcuts.command.toggle_all_cards.label"
            },
            {
              "modifiers": ["⌘", "⇧"],
              "shortcuts": ["shortcuts.command.toggle_background_card.key"],
              "text": "shortcuts.command.toggle_background_card.label"
            },
            {
              "modifiers": ["⌘", "⇧"],
              "shortcuts": ["shortcuts.command.toggle_history_card.key"],
              "text": "shortcuts.command.toggle_history_card.label"
            },
            {
              "modifiers": ["⌘", "⇧"],
              "shortcuts": ["shortcuts.command.toggle_location_card.key"],
              "text": "shortcuts.command.toggle_location_card.label"
            },
            {
              "modifiers": ["⌘", "⇧"],
              "shortcuts": ["shortcuts.command.toggle_measurement_card.key"],
              "text": "shortcuts.command.toggle_measurement_card.label"
            }
          ]
        }
      ]
    }
  ]
}
